{
  "project_info": {
    "project_number": "127083011483",
    "firebase_url": "https://homeapp-7e086-default-rtdb.firebaseio.com",
    "project_id": "homeapp-7e086",
    "storage_bucket": "homeapp-7e086.appspot.com"
  },
  "client": [
    {
      "client_info": {
        "mobilesdk_app_id": "1:127083011483:android:358a9a67f86e266452d53e",
        "android_client_info": {
          "package_name": "com.example.homeapp"
        }
      },
      "oauth_client": [
        {
          "client_id": "127083011483-lvnldhjsidc05ngmlausrv44v7156cc6.apps.googleusercontent.com",
          "client_type": 3
        }
      ],
      "api_key": [
        {
          "current_key": "AIzaSyAKwRFGWzulSnG0HiCWnaKsY1HUG9gpo5c"
        }
      ],
      "services": {
        "appinvite_service": {
          "other_platform_oauth_client": [
            {
              "client_id": "127083011483-lvnldhjsidc05ngmlausrv44v7156cc6.apps.googleusercontent.com",
              "client_type": 3
            }
          ]
        }
      }
    }
  ],
  "configuration_version": "1"
}